Metadata-Version: 2.1
Name: lit-lib
Version: 1.0a0
Summary: Короткое описание твоего проекта на PyPi
Home-page: https://github.com/DiorDS/lit_lib
Author: Ilya G
Author-email: phone.mas@yandex.ru
Keywords: localisation lit translate
Requires: deep_translator
